dayu_path/__init__.py
dayu_path/base.py
dayu_path/constants.py
dayu_path/errors.py
dayu_path/plugin.py
dayu_path/test/__init__.py
dayu_path/test/test_dayu_path.py
dayu_path/test/test_dayu_path_plugin.py
dayu_path-0.5.2.dist-info/LICENSE
dayu_path-0.5.2.dist-info/METADATA
dayu_path-0.5.2.dist-info/WHEEL
dayu_path-0.5.2.dist-info/top_level.txt
dayu_path-0.5.2.dist-info/RECORD
