Metadata-Version: 2.1
Name: dayu-path
Version: 0.5.2
Summary: a python path lib optimized for Movie industry. Support scan for sequence files, extract frame count and many other useful functions.
Home-page: https://github.com/phenom-films/dayu_path
Author: andyguo
Author-email: andyguo@phenom-films.com
License: MIT
Platform: UNKNOWN
Classifier: Operating System :: OS Independent
Classifier: Programming Language :: Python
Classifier: Programming Language :: Python :: Implementation
Classifier: Programming Language :: Python :: 2
Classifier: Programming Language :: Python :: 2.7
